{
  "annotations": {"list": []},
  "editable": true,
  "graphTooltip": 0,
  "panels": [
    {
      "type": "stat",
      "title": "Core API Requests",
      "datasource": {"type": "prometheus", "uid": "prometheus"},
      "targets": [{"expr": "fitlife_http_requests_total", "refId": "A"}],
      "gridPos": {"h": 8, "w": 8, "x": 0, "y": 0}
    },
    {
      "type": "stat",
      "title": "Core API Errors",
      "datasource": {"type": "prometheus", "uid": "prometheus"},
      "targets": [{"expr": "fitlife_http_errors_total", "refId": "A"}],
      "gridPos": {"h": 8, "w": 8, "x": 8, "y": 0}
    },
    {
      "type": "stat",
      "title": "Membership Cache Hits",
      "datasource": {"type": "prometheus", "uid": "prometheus"},
      "targets": [{"expr": "fitlife_membership_cache_hits_total", "refId": "A"}],
      "gridPos": {"h": 8, "w": 8, "x": 16, "y": 0}
    },
    {
      "type": "timeseries",
      "title": "Service Request Counters",
      "datasource": {"type": "prometheus", "uid": "prometheus"},
      "targets": [
        {"expr": "fitlife_http_requests_total", "legendFormat": "core", "refId": "A"},
        {"expr": "fitlife_analytics_requests_total", "legendFormat": "analytics", "refId": "B"},
        {"expr": "fitlife_membership_requests_total", "legendFormat": "membership", "refId": "C"}
      ],
      "gridPos": {"h": 10, "w": 24, "x": 0, "y": 8}
    }
  ],
  "refresh": "10s",
  "schemaVersion": 39,
  "tags": ["fitlife", "spqm", "level-3"],
  "templating": {"list": []},
  "time": {"from": "now-15m", "to": "now"},
  "timezone": "browser",
  "title": "FitLife SPQM Overview",
  "uid": "fitlife-spqm-overview",
  "version": 1
}
